aiohttp_oauth2_session/__init__.py
aiohttp_oauth2_session/py.typed
aiohttp_oauth2_session/session.py
aiohttp_oauth2_session/typed_oauthlib.py
aiohttp_oauth2_session-0.1.1.dist-info/METADATA
aiohttp_oauth2_session-0.1.1.dist-info/WHEEL
aiohttp_oauth2_session-0.1.1.dist-info/RECORD
